sqla_handler.py
ss_sqla_handler-0.0.1.dist-info/METADATA
ss_sqla_handler-0.0.1.dist-info/WHEEL
ss_sqla_handler-0.0.1.dist-info/top_level.txt
ss_sqla_handler-0.0.1.dist-info/RECORD
