Metadata-Version: 2.4
Name: ss-sqla_handler
Version: 0.0.1
Summary: Thin wrapper for sqlalchemy with support for Pandas
Author-email: Julian Briggs <julian.briggs@sheffield.ac.uk>
License-Expression: MIT
Project-URL: Homepage, https://github.com/pypa/ss-sqla_handler
Project-URL: Issues, https://github.com/pypa/ss-sqla_handler/issues
Classifier: Programming Language :: Python :: 3
Classifier: Operating System :: OS Independent
Requires-Python: >=3.12
